golftrainer/__init__.py
golftrainer/__version__.py
golftrainer/factory.py
golftrainer/golf_data.py
golftrainer-1.0.2.dist-info/LICENSE.txt
golftrainer-1.0.2.dist-info/METADATA
golftrainer-1.0.2.dist-info/WHEEL
golftrainer-1.0.2.dist-info/entry_points.txt
golftrainer-1.0.2.dist-info/top_level.txt
golftrainer-1.0.2.dist-info/RECORD
