Metadata-Version: 2.1
Name: golftrainer
Version: 1.0.2
Summary: Analyze a golf swing looking at critical points.
Home-page: https://github.com/sanjeevs/golftrainer
Author: Sanjeev Singh
Author-email: snjvsingh123@gmail.com
License: UNKNOWN
Platform: UNKNOWN
Classifier: Programming Language :: Python :: 3
Classifier: Programming Language :: Python :: 3.6
Classifier: Programming Language :: Python :: 3.7
Classifier: License :: OSI Approved :: MIT License
Classifier: Operating System :: OS Independent
Classifier: Development Status :: 3 - Alpha
License-File: LICENSE.txt
Requires-Dist: pandas
Requires-Dist: numpy
Provides-Extra: dev
Requires-Dist: pytest >=3.7 ; extra == 'dev'
Requires-Dist: check-manifest ; extra == 'dev'
Requires-Dist: twine ; extra == 'dev'
